[
    {
        "id": 1469013041290
    },
    {
        "id": 1469013062140,
        "author": "Ryan",
        "text": "Nice one"
    },
    {
        "id": 1469013123819,
        "author": "Samuele Zaza",
        "text": "Could you show some test code?"
    },
    {
        "id": 1471074137707,
        "author": "Chris",
        "text": "Hi"
    },
    {
        "id": 1471074253479,
        "author": "Chris",
        "text": "Hi"
    },
    {
        "id": 1471074306464,
        "author": "Chris",
        "text": "Hi"
    },
    {
        "id": 1471074385294,
        "author": "Chris",
        "text": "Hi"
    },
    {
        "id": 1471074615038,
        "author": "Chris",
        "text": "Hi"
    },
    {
        "id": 1471075083535,
        "author": "Chris",
        "text": "Hi"
    },
    {
        "id": 1490977055941,
        "author": "Acadgild",
        "text": "Comment added by Acadgild - Edited"
    },
    {
        "id": 1491622096910
    },
    {
        "id": 1491622235834
    },
    {
        "id": 1491622395495
    },
    {
        "id": 1491622782258
    }
]